DESCRIPTION.rst
MANIFEST.in
setup.cfg
setup.py
dry/__init__.py
dry/__main__.py
dry.egg-info/PKG-INFO
dry.egg-info/SOURCES.txt
dry.egg-info/dependency_links.txt
dry.egg-info/entry_points.txt
dry.egg-info/requires.txt
dry.egg-info/top_level.txt